LICENSE
MANIFEST.in
README.md
pyproject.toml
setup.cfg
setup.py
src/defederate/__init__.py
src/defederate/activitypub.py
src/defederate/blocklist_parsers.py
src/defederate/cli.py
src/defederate/const.py
src/defederate/errors.py
src/defederate/server_api.py
src/defederate.egg-info/PKG-INFO
src/defederate.egg-info/SOURCES.txt
src/defederate.egg-info/dependency_links.txt
src/defederate.egg-info/entry_points.txt
src/defederate.egg-info/not-zip-safe
src/defederate.egg-info/requires.txt
src/defederate.egg-info/top_level.txt
src/defederate/plugin/__init__.py
src/defederate/plugin/markdown.py
src/defederate/plugin/mastodon3.py
src/defederate/plugin/mastodon4.py